design.sv
`timescale 1ns / 1ps
// ======================================================================
// uart_led_sensor_top (Optimized)
// - Immediate LED ON/OFF when a full 3-char command is received
// - Accepts only ON1..ON8 and OF1..OF8 (others ignored)
// - No newline required
// - Robust against command overlap (buffer cleared after decode)
// ======================================================================
module uart_led_sensor_top(
    input  wire        i_Clock,    // 50 MHz clock
    input  wire        i_Rst,      // synchronous active-high reset
    input  wire        FPGA_RXD,   // UART RX (to FPGA)
    output wire        FPGA_TXD,   // UART TX (from FPGA)
    output reg  [7:0]  o_LEDs      // 8 LEDs (o_LEDs[0] -> LED1)
);

    // ---------------- PARAMETERS ----------------
    parameter integer CLOCK_RATE = 50_000_000;
    parameter integer BAUD_RATE  = 1_000_000; // fast for simulation
    localparam integer CLKS_PER_BIT = CLOCK_RATE / BAUD_RATE;

    // ---------------- TX (simple) ----------------
    reg [15:0] tx_cnt;
    reg [3:0]  tx_bit;
    reg [9:0]  tx_shift;
    reg        tx_line = 1'b1;
    reg        tx_busy = 1'b0;
    reg        tx_done = 1'b0;
    assign FPGA_TXD = tx_line;

    // ---------------- RX ----------------
    reg [15:0] rx_cnt;
    reg [2:0]  rx_bit;
    reg [7:0]  rx_byte;
    reg        rx_dv;
    reg [2:0]  rx_state;
    reg r1, r2;
    wire rx_sync;
    always @(posedge i_Clock) begin r1 <= FPGA_RXD; r2 <= r1; end
    assign rx_sync = r2;

    localparam RX_IDLE  = 3'd0,
               RX_START = 3'd1,
               RX_DATA  = 3'd2,
               RX_STOP  = 3'd3;

    always @(posedge i_Clock) begin
        if (i_Rst) begin
            rx_state <= RX_IDLE;
            rx_cnt   <= 0;
            rx_bit   <= 0;
            rx_byte  <= 8'd0;
            rx_dv    <= 1'b0;
        end else begin
            rx_dv <= 1'b0;
            case (rx_state)
                RX_IDLE: if (!rx_sync) begin rx_state <= RX_START; rx_cnt <= 0; end
                RX_START: begin
                    if (rx_cnt == (CLKS_PER_BIT/2)) begin
                        if (!rx_sync) begin
                            rx_state <= RX_DATA;
                            rx_bit <= 0;
                        end else begin
                            rx_state <= RX_IDLE;
                        end
                        rx_cnt <= 0;
                    end else rx_cnt <= rx_cnt + 1;
                end
                RX_DATA: begin
                    if (rx_cnt < CLKS_PER_BIT-1) rx_cnt <= rx_cnt + 1;
                    else begin
                        rx_cnt <= 0;
                        rx_byte[rx_bit] <= rx_sync;
                        if (rx_bit < 7) rx_bit <= rx_bit + 1;
                        else rx_state <= RX_STOP;
                    end
                end
                RX_STOP: begin
                    if (rx_cnt < CLKS_PER_BIT-1) rx_cnt <= rx_cnt + 1;
                    else begin
                        rx_cnt <= 0;
                        rx_state <= RX_IDLE;
                        rx_dv <= 1'b1; // one-cycle pulse: byte received
                    end
                end
            endcase
        end
    end

    // ---------------- Command buffer (sliding 3-byte window) ----------------
    // We always form next_cmd = {cmd_buf[15:0], rx_byte} on rx_dv and evaluate it.
    reg [23:0] cmd_buf; // holds last upto-3 bytes; cleared after decode

    // temporary wire to form the candidate 3-char command (uses current cmd_buf + new byte)
    wire [23:0] next_cmd = {cmd_buf[15:0], rx_byte};

    // ---------------- main command decode & LED control ----------------
    // We act immediately when rx_dv pulses and next_cmd matches ONx or OFx.
    always @(posedge i_Clock) begin
        if (i_Rst) begin
            o_LEDs  <= 8'b0;
            cmd_buf <= 24'b0;
            // TX initial state
            tx_line <= 1'b1;
            tx_busy <= 1'b0;
            tx_done <= 1'b0;
            tx_cnt  <= 0;
            tx_bit  <= 0;
            tx_shift<= 10'b1111111111;
        end else begin
            tx_done <= 1'b0;

            if (rx_dv) begin
                // Evaluate candidate command formed by existing buffer plus new byte
                // If it matches, act and clear buffer. Otherwise, store next_cmd and wait.
                // Match "ONx"
                if ((next_cmd[23:8] == {8'h4F, 8'h4E}) && (next_cmd[7:0] >= "1") && (next_cmd[7:0] <= "8")) begin
                    // turn ON the requested LED immediately
                    integer idx;
                    idx = next_cmd[7:0] - "1";
                    o_LEDs[idx] <= 1'b1;
                    // clear buffer for next command
                    cmd_buf <= 24'b0;
                end
                // Match "OFx"
                else if ((next_cmd[23:8] == {8'h4F, 8'h46}) && (next_cmd[7:0] >= "1") && (next_cmd[7:0] <= "8")) begin
                    integer idx;
                    idx = next_cmd[7:0] - "1";
                    o_LEDs[idx] <= 1'b0;
                    cmd_buf <= 24'b0;
                end
                // Optionally accept STATUS (starts with "STA") -> begin TX later (simple example)
                else if (next_cmd[23:8] == {8'h53,8'h54}) begin
                    // If "STA" is being typed, we won't act until more bytes (not used here)
                    // Save next_cmd to buffer so future bytes can complete STATUS sequence
                    cmd_buf <= next_cmd;
                end
                else begin
                    // Not recognised yet - keep sliding window (store next_cmd), this allows overlapping commands
                    cmd_buf <= next_cmd;
                    // To prevent cmd_buf from growing stale with non-ASCII, we could add extra checks:
                    // If next_cmd contains non-printable bytes, we could clear — for simplicity we allow sliding.
                end
            end
            // (TX logic can be added/kept here if STATUS response is needed; omitted for clarity)
        end
    end

    // (Optional) Simple TX engine placeholder - kept minimal so design compiles
    // Here we don't automatically send STATUS bytes; TX logic can be added as needed.

endmodule

testbench.sv
`timescale 1ns / 1ps
// ======================================================================
// tb_uart_led_sensor - Testbench for optimized design
// - Sends ON/OFF commands, including invalid ones to verify ignore behavior
// - Dumps Wave.vcd for GTKWave/EPWave
// ======================================================================
module tb_uart_led_sensor;

    // DUT signals
    logic i_Clock;
    logic i_Rst;
    logic FPGA_RXD;
    wire  FPGA_TXD;
    wire [7:0] o_LEDs;

    // Instantiate DUT
    uart_led_sensor_top dut (
        .i_Clock(i_Clock),
        .i_Rst(i_Rst),
        .FPGA_RXD(FPGA_RXD),
        .FPGA_TXD(FPGA_TXD),
        .o_LEDs(o_LEDs)
    );

    // Clock: 50 MHz
    localparam real CLK_PERIOD_NS = 20.0;
    initial begin
        i_Clock = 1'b0;
        forever #(CLK_PERIOD_NS/2.0) i_Clock = ~i_Clock;
    end

    // UART timing: must match design BAUD_RATE = 1_000_000
    localparam int BAUD_RATE = 1_000_000;
    real BIT_PERIOD_NS = 1_000_000_000.0 / BAUD_RATE; // ns per bit

    // Send a single UART byte (8N1)
    task automatic send_byte(input [7:0] b);
        int i;
        begin
            // start bit
            FPGA_RXD <= 1'b0; #(BIT_PERIOD_NS);
            // data LSB first
            for (i = 0; i < 8; i = i + 1) begin
                FPGA_RXD <= b[i]; #(BIT_PERIOD_NS);
            end
            // stop bit
            FPGA_RXD <= 1'b1; #(BIT_PERIOD_NS);
        end
    endtask

    // Send ASCII command (no newline required)
    task automatic send_command(input string s);
        int i;
        begin
            for (i = 0; i < s.len(); i = i + 1) begin
                send_byte(s[i]);
                // small gap between characters (not required but keeps things clean)
                #(BIT_PERIOD_NS * 2);
            end
            // brief gap after command so decode happens in waveform nicely
            #(BIT_PERIOD_NS * 8);
        end
    endtask

    // Build test sequence
    initial begin
        // waveform dump
        $dumpfile("Wave.vcd");
        $dumpvars(0, tb_uart_led_sensor);

        // init
        FPGA_RXD = 1'b1; // idle line high
        i_Rst = 1'b1;
        #200;
        i_Rst = 1'b0;
        #2000;

        $display("--- TEST START ---");

        // Valid: ON1 -> LED0
        send_command("ON1");
        #1000;
        // Valid: ON2 -> LED1
        send_command("ON2");
        #1000;
        // Valid: ON8 -> LED7
        send_command("ON8");
        #1000;
        // Invalid: ON9 -> should be ignored (no LED change)
        send_command("ON9");
        #1000;
        // Invalid random -> ignored
        send_command("ABC");
        #1000;
        // Turn OFF a LED: OF2 -> LED1 clear
        send_command("OF2");
        #1000;
        // Turn OFF LED8: OF8
        send_command("OF8");
        #1000;
        // Turn ON LED3
        send_command("ON3");
        #1000;

        $display("--- CHECK LED VALUES IN LOG / WAVEFORM ---");
        #5000;

        $display("--- TEST COMPLETE ---");
        #100;
        $finish;
    end

    // Monitor concise output
    initial begin
        $monitor("[%0t ns] LEDs=%b RXD=%b TXD=%b", $time, o_LEDs, FPGA_RXD, FPGA_TXD);
    end

endmodule

Wave.vcd
$date
	Sun Nov  9 05:59:42 2025
$end
$version
	Icarus Verilog
$end
$timescale
	1ps
$end
$scope module tb_uart_led_sensor $end
$var wire 8 ! o_LEDs [7:0] $end
$var wire 1 " FPGA_TXD $end
$var parameter 32 # BAUD_RATE $end
$var real 1 $ CLK_PERIOD_NS $end
$var reg 1 % FPGA_RXD $end
$var reg 1 & i_Clock $end
$var reg 1 ' i_Rst $end
$var real 1 ( BIT_PERIOD_NS $end
$scope module dut $end
$var wire 1 % FPGA_RXD $end
$var wire 1 " FPGA_TXD $end
$var wire 1 & i_Clock $end
$var wire 1 ' i_Rst $end
$var wire 1 ) rx_sync $end
$var wire 24 * next_cmd [23:0] $end
$var parameter 32 + BAUD_RATE $end
$var parameter 32 , CLKS_PER_BIT $end
$var parameter 32 - CLOCK_RATE $end
$var parameter 3 . RX_DATA $end
$var parameter 3 / RX_IDLE $end
$var parameter 3 0 RX_START $end
$var parameter 3 1 RX_STOP $end
$var reg 24 2 cmd_buf [23:0] $end
$var reg 8 3 o_LEDs [7:0] $end
$var reg 1 4 r1 $end
$var reg 1 5 r2 $end
$var reg 3 6 rx_bit [2:0] $end
$var reg 8 7 rx_byte [7:0] $end
$var reg 16 8 rx_cnt [15:0] $end
$var reg 1 9 rx_dv $end
$var reg 3 : rx_state [2:0] $end
$var reg 4 ; tx_bit [3:0] $end
$var reg 1 < tx_busy $end
$var reg 16 = tx_cnt [15:0] $end
$var reg 1 > tx_done $end
$var reg 1 ? tx_line $end
$var reg 10 @ tx_shift [9:0] $end
$scope begin $unm_blk_18 $end
$var integer 32 A idx [31:0] $end
$upscope $end
$scope begin $unm_blk_19 $end
$var integer 32 B idx [31:0] $end
$upscope $end
$upscope $end
$scope task send_byte $end
$upscope $end
$scope task send_command $end
$upscope $end
$upscope $end
$enddefinitions $end
$comment Show the parameter values. $end
$dumpall
b11 1
b1 0
b0 /
b10 .
b10111110101111000010000000 -
b110010 ,
b11110100001001000000 +
r20 $
b11110100001001000000 #
$end
#0
$dumpvars
bx B
bx A
bx @
1?
0>
bx =
0<
bx ;
bx :
x9
bx 8
bx 7
bx 6
x5
x4
bx 3
bx 2
bx *
x)
r1000 (
1'
0&
1%
1"
bx !
$end
#10000
14
09
b0 *
b0 7
b0 6
b0 8
b0 :
b1111111111 @
b0 ;
b0 =
b0 2
b0 !
b0 3
1&
#20000
0&
#30000
1)
15
1&
#40000
0&
#50000
1&
#60000
0&
#70000
1&
#80000
0&
#90000
1&
#100000
0&
#110000
1&
#120000
0&
#130000
1&
#140000
0&
#150000
1&
#160000
0&
#170000
1&
#180000
0&
#190000
1&
#200000
0&
0'
#210000
1&
#220000
0&
#230000
1&
#240000
0&
#250000
1&
#260000
0&
#270000
1&
#280000
0&
#290000
1&
#300000
0&
#310000
1&
#320000
0&
#330000
1&
#340000
0&
#350000
1&
#360000
0&
#370000
1&
#380000
0&
#390000
1&
#400000
0&
#410000
1&
#420000
0&
#430000
1&
#440000
0&
#450000
1&
#460000
0&
#470000
1&
#480000
0&
#490000
1&
#500000
0&
#510000
1&
#520000
0&
#530000
1&
#540000
0&
#550000
1&
#560000
0&
#570000
1&
#580000
0&
#590000
1&
#600000
0&
#610000
1&
#620000
0&
#630000
1&
#640000
0&
#650000
1&
#660000
0&
#670000
1&
#680000
0&
#690000
1&
#700000
0&
#710000
1&
#720000
0&
#730000
1&
#740000
0&
#750000
1&
#760000
0&
#770000
1&
#780000
0&
#790000
1&
#800000
0&
#810000
1&
#820000
0&
#830000
1&
#840000
0&
#850000
1&
#860000
0&
#870000
1&
#880000
0&
#890000
1&
#900000
0&
#910000
1&
#920000
0&
#930000
1&
#940000
0&
#950000
1&
#960000
0&
#970000
1&
#980000
0&
#990000
1&
#1000000
0&
#1010000
1&
#1020000
0&
#1030000
1&
#1040000
0&
#1050000
1&
#1060000
0&
#1070000
1&
#1080000
0&
#1090000
1&
#1100000
0&
#1110000
1&
#1120000
0&
#1130000
1&
#1140000
0&
#1150000
1&
#1160000
0&
#1170000
1&
#1180000
0&
#1190000
1&
#1200000
0&
#1210000
1&
#1220000
0&
#1230000
1&
#1240000
0&
#1250000
1&
#1260000
0&
#1270000
1&
#1280000
0&
#1290000
1&
#1300000
0&
#1310000
1&
#1320000
0&
#1330000
1&
#1340000
0&
#1350000
1&
#1360000
0&
#1370000
1&
#1380000
0&
#1390000
1&
#1400000
0&
#1410000
1&
#1420000
0&
#1430000
1&
#1440000
0&
#1450000
1&
#1460000
0&
#1470000
1&
#1480000
0&
#1490000
1&
#1500000
0&
#1510000
1&
#1520000
0&
#1530000
1&
#1540000
0&
#1550000
1&
#1560000
0&
#1570000
1&
#1580000
0&
#1590000
1&
#1600000
0&
#1610000
1&
#1620000
0&
#1630000
1&
#1640000
0&
#1650000
1&
#1660000
0&
#1670000
1&
#1680000
0&
#1690000
1&
#1700000
0&
#1710000
1&
#1720000
0&
#1730000
1&
#1740000
0&
#1750000
1&
#1760000
0&
#1770000
1&
#1780000
0&
#1790000
1&
#1800000
0&
#1810000
1&
#1820000
0&
#1830000
1&
#1840000
0&
#1850000
1&
#1860000
0&
#1870000
1&
#1880000
0&
#1890000
1&
#1900000
0&
#1910000
1&
#1920000
0&
#1930000
1&
#1940000
0&
#1950000
1&
#1960000
0&
#1970000
1&
#1980000
0&
#1990000
1&
#2000000
0&
#2010000
1&
#2020000
0&
#2030000
1&
#2040000
0&
#2050000
1&
#2060000
0&
#2070000
1&
#2080000
0&
#2090000
1&
#2100000
0&
#2110000
1&
#2120000
0&
#2130000
1&
#2140000
0&
#2150000
1&
#2160000
0&
#2170000
1&
#2180000
0&
#2190000
1&
#2200000
0%
0&
#2210000
04
1&
#2220000
0&
#2230000
0)
05
1&
#2240000
0&
#2250000
b1 :
1&
#2260000
0&
#2270000
b1 8
1&
#2280000
0&
#2290000
b10 8
1&
#2300000
0&
#2310000
b11 8
1&
#2320000
0&
#2330000
b100 8
1&
#2340000
0&
#2350000
b101 8
1&
#2360000
0&
#2370000
b110 8
1&
#2380000
0&
#2390000
b111 8
1&
#2400000
0&
#2410000
b1000 8
1&
#2420000
0&
#2430000
b1001 8
1&
#2440000
0&
#2450000
b1010 8
1&
#2460000
0&
#2470000
b1011 8
1&
#2480000
0&
#2490000
b1100 8
1&
#2500000
0&
#2510000
b1101 8
1&
#2520000
0&
#2530000
b1110 8
1&
#2540000
0&
#2550000
b1111 8
1&
#2560000
0&
#2570000
b10000 8
1&
#2580000
0&
#2590000
b10001 8
1&
#2600000
0&
#2610000
b10010 8
1&
#2620000
0&
#2630000
b10011 8
1&
#2640000
0&
#2650000
b10100 8
1&
#2660000
0&
#2670000
b10101 8
1&
#2680000
0&
#2690000
b10110 8
1&
#2700000
0&
#2710000
b10111 8
1&
#2720000
0&
#2730000
b11000 8
1&
#2740000
0&
#2750000
b11001 8
1&
#2760000
0&
#2770000
b0 8
b10 :
1&
#2780000
0&
#2790000
b1 8
1&
#2800000
0&
#2810000
b10 8
1&
#2820000
0&
#2830000
b11 8
1&
#2840000
0&
#2850000
b100 8
1&
#2860000
0&
#2870000
b101 8
1&
#2880000
0&
#2890000
b110 8
1&
#2900000
0&
#2910000
b111 8
1&
#2920000
0&
#2930000
b1000 8
1&
#2940000
0&
#2950000
b1001 8
1&
#2960000
0&
#2970000
b1010 8
1&
#2980000
0&
#2990000
b1011 8
1&
#3000000
0&
#3010000
b1100 8
1&
#3020000
0&
#3030000
b1101 8
1&
#3040000
0&
#3050000
b1110 8
1&
#3060000
0&
#3070000
b1111 8
1&
#3080000
0&
#3090000
b10000 8
1&
#3100000
0&
#3110000
b10001 8
1&
#3120000
0&
#3130000
b10010 8
1&
#3140000
0&
#3150000
b10011 8
1&
#3160000
0&
#3170000
b10100 8
1&
#3180000
0&
#3190000
b10101 8
1&
#3200000
1%
0&
#3210000
14
b10110 8
1&
#3220000
0&
#3230000
b10111 8
1)
15
1&
#3240000
0&
#3250000
b11000 8
1&
#3260000
0&
#3270000
b11001 8
1&
#3280000
0&
#3290000
b11010 8
1&
#3300000
0&
#3310000
b11011 8
1&
#3320000
0&
#3330000
b11100 8
1&
#3340000
0&
#3350000
b11101 8
1&
#3360000
0&
#3370000
b11110 8
1&
#3380000
0&
#3390000
b11111 8
1&
#3400000
0&
#3410000
b100000 8
1&
#3420000
0&
#3430000
b100001 8
1&
#3440000
0&
#3450000
b100010 8
1&
#3460000
0&
#3470000
b100011 8
1&
#3480000
0&
#3490000
b100100 8
1&
#3500000
0&
#3510000
b100101 8
1&
#3520000
0&
#3530000
b100110 8
1&
#3540000
0&
#3550000
b100111 8
1&
#3560000
0&
#3570000
b101000 8
1&
#3580000
0&
#3590000
b101001 8
1&
#3600000
0&
#3610000
b101010 8
1&
#3620000
0&
#3630000
b101011 8
1&
#3640000
0&
#3650000
b101100 8
1&
#3660000
0&
#3670000
b101101 8
1&
#3680000
0&
#3690000
b101110 8
1&
#3700000
0&
#3710000
b101111 8
1&
#3720000
0&
#3730000
b110000 8
1&
#3740000
0&
#3750000
b110001 8
1&
#3760000
0&
#3770000
b1 6
b1 *
b1 7
b0 8
1&
#3780000
0&
#3790000
b1 8
1&
#3800000
0&
#3810000
b10 8
1&
#3820000
0&
#3830000
b11 8
1&
#3840000
0&
#3850000
b100 8
1&
#3860000
0&
#3870000
b101 8
1&
#3880000
0&
#3890000
b110 8
1&
#3900000
0&
#3910000
b111 8
1&
#3920000
0&
#3930000
b1000 8
1&
#3940000
0&
#3950000
b1001 8
1&
#3960000
0&
#3970000
b1010 8
1&
#3980000
0&
#3990000
b1011 8
1&
#4000000
0&
#4010000
b1100 8
1&
#4020000
0&
#4030000
b1101 8
1&
#4040000
0&
#4050000
b1110 8
1&
#4060000
0&
#4070000
b1111 8
1&
#4080000
0&
#4090000
b10000 8
1&
#4100000
0&
#4110000
b10001 8
1&
#4120000
0&
#4130000
b10010 8
1&
#4140000
0&
#4150000
b10011 8
1&
#4160000
0&
#4170000
b10100 8
1&
#4180000
0&
#4190000
b10101 8
1&
#4200000
0&
#4210000
b10110 8
1&
#4220000
0&
#4230000
b10111 8
1&
#4240000
0&
#4250000
b11000 8
1&
#4260000
0&
#4270000
b11001 8
1&
#4280000
0&
#4290000
b11010 8
1&
#4300000
0&
#4310000
b11011 8
1&
#4320000
0&
#4330000
b11100 8
1&
#4340000
0&
#4350000
b11101 8
1&
#4360000
0&
#4370000
b11110 8
1&
#4380000
0&
#4390000
b11111 8
1&
#4400000
0&
#4410000
b100000 8
1&
#4420000
0&
#4430000
b100001 8
1&
#4440000
0&
#4450000
b100010 8
1&
#4460000
0&
#4470000
b100011 8
1&
#4480000
0&
#4490000
b100100 8
1&
#4500000
0&
#4510000
b100101 8
1&
#4520000
0&
#4530000
b100110 8
1&
#4540000
0&
#4550000
b100111 8
1&
#4560000
0&
#4570000
b101000 8
1&
#4580000
0&
#4590000
b101001 8
1&
#4600000
0&
#4610000
b101010 8
1&
#4620000
0&
#4630000
b101011 8
1&
#4640000
0&
#4650000
b101100 8
1&
#4660000
0&
#4670000
b101101 8
1&
#4680000
0&
#4690000
b101110 8
1&
#4700000
0&
#4710000
b101111 8
1&
#4720000
0&
#4730000
b110000 8
1&
#4740000
0&
#4750000
b110001 8
1&
#4760000
0&
#4770000
b10 6
b11 *
b11 7
b0 8
1&
#4780000
0&
#4790000
b1 8
1&
#4800000
0&
#4810000
b10 8
1&
#4820000
0&
#4830000
b11 8
1&
#4840000
0&
#4850000
b100 8
1&
#4860000
0&
#4870000
b101 8
1&
#4880000
0&
#4890000
b110 8
1&
#4900000
0&
#4910000
b111 8
1&
#4920000
0&
#4930000
b1000 8
1&
#4940000
0&
#4950000
b1001 8
1&
#4960000
0&
#4970000
b1010 8
1&
#4980000
0&
#4990000
b1011 8
1&
#5000000
0&
#5010000
b1100 8
1&
#5020000
0&
#5030000
b1101 8
1&
#5040000
0&
#5050000
b1110 8
1&
#5060000
0&
#5070000
b1111 8
1&
#5080000
0&
#5090000
b10000 8
1&
#5100000
0&
#5110000
b10001 8
1&
#5120000
0&
#5130000
b10010 8
1&
#5140000
0&
#5150000
b10011 8
1&
#5160000
0&
#5170000
b10100 8
1&
#5180000
0&
#5190000
b10101 8
1&
#5200000
0&
#5210000
b10110 8
1&
#5220000
0&
#5230000
b10111 8
1&
#5240000
0&
#5250000
b11000 8
1&
#5260000
0&
#5270000
b11001 8
1&
#5280000
0&
#5290000
b11010 8
1&
#5300000
0&
#5310000
b11011 8
1&
#5320000
0&
#5330000
b11100 8
1&
#5340000
0&
#5350000
b11101 8
1&
#5360000
0&
#5370000
b11110 8
1&
#5380000
0&
#5390000
b11111 8
1&
#5400000
0&
#5410000
b100000 8
1&
#5420000
0&
#5430000
b100001 8
1&
#5440000
0&
#5450000
b100010 8
1&
#5460000
0&
#5470000
b100011 8
1&
#5480000
0&
#5490000
b100100 8
1&
#5500000
0&
#5510000
b100101 8
1&
#5520000
0&
#5530000
b100110 8
1&
#5540000
0&
#5550000
b100111 8
1&
#5560000
0&
#5570000
b101000 8
1&
#5580000
0&
#5590000
b101001 8
1&
#5600000
0&
#5610000
b101010 8
1&
#5620000
0&
#5630000
b101011 8
1&
#5640000
0&
#5650000
b101100 8
1&
#5660000
0&
#5670000
b101101 8
1&
#5680000
0&
#5690000
b101110 8
1&
#5700000
0&
#5710000
b101111 8
1&
#5720000
0&
#5730000
b110000 8
1&
#5740000
0&
#5750000
b110001 8
1&
#5760000
0&
#5770000
b11 6
b111 *
b111 7
b0 8
1&
#5780000
0&
#5790000
b1 8
1&
#5800000
0&
#5810000
b10 8
1&
#5820000
0&
#5830000
b11 8
1&
#5840000
0&
#5850000
b100 8
1&
#5860000
0&
#5870000
b101 8
1&
#5880000
0&
#5890000
b110 8
1&
#5900000
0&
#5910000
b111 8
1&
#5920000
0&
#5930000
b1000 8
1&
#5940000
0&
#5950000
b1001 8
1&
#5960000
0&
#5970000
b1010 8
1&
#5980000
0&
#5990000
b1011 8
1&
#6000000
0&
#6010000
b1100 8
1&
#6020000
0&
#6030000
b1101 8
1&
#6040000
0&
#6050000
b1110 8
1&
#6060000
0&
#6070000
b1111 8
1&
#6080000
0&
#6090000
b10000 8
1&
#6100000
0&
#6110000
b10001 8
1&
#6120000
0&
#6130000
b10010 8
1&
#6140000
0&
#6150000
b10011 8
1&
#6160000
0&
#6170000
b10100 8
1&
#6180000
0&
#6190000
b10101 8
1&
#6200000
0&
#6210000
b10110 8
1&
#6220000
0&
#6230000
b10111 8
1&
#6240000
0&
#6250000
b11000 8
1&
#6260000
0&
#6270000
b11001 8
1&
#6280000
0&
#6290000
b11010 8
1&
#6300000
0&
#6310000
b11011 8
1&
#6320000
0&
#6330000
b11100 8
1&
#6340000
0&
#6350000
b11101 8
1&
#6360000
0&
#6370000
b11110 8
1&
#6380000
0&
#6390000
b11111 8
1&
#6400000
0&
#6410000
b100000 8
1&
#6420000
0&
#6430000
b100001 8
1&
#6440000
0&
#6450000
b100010 8
1&
#6460000
0&
#6470000
b100011 8
1&
#6480000
0&
#6490000
b100100 8
1&
#6500000
0&
#6510000
b100101 8
1&
#6520000
0&
#6530000
b100110 8
1&
#6540000
0&
#6550000
b100111 8
1&
#6560000
0&
#6570000
b101000 8
1&
#6580000
0&
#6590000
b101001 8
1&
#6600000
0&
#6610000
b101010 8
1&
#6620000
0&
#6630000
b101011 8
1&
#6640000
0&
#6650000
b101100 8
1&
#6660000
0&
#6670000
b101101 8
1&
#6680000
0&
#6690000
b101110 8
1&
#6700000
0&
#6710000
b101111 8
1&
#6720000
0&
#6730000
b110000 8
1&
#6740000
0&
#6750000
b110001 8
1&
#6760000
0&
#6770000
b100 6
b1111 *
b1111 7
b0 8
1&
#6780000
0&
#6790000
b1 8
1&
#6800000
0&
#6810000
b10 8
1&
#6820000
0&
#6830000
b11 8
1&
#6840000
0&
#6850000
b100 8
1&
#6860000
0&
#6870000
b101 8
1&
#6880000
0&
#6890000
b110 8
1&
#6900000
0&
#6910000
b111 8
1&
#6920000
0&
#6930000
b1000 8
1&
#6940000
0&
#6950000
b1001 8
1&
#6960000
0&
#6970000
b1010 8
1&
#6980000
0&
#6990000
b1011 8
1&
#7000000
0&
#7010000
b1100 8
1&
#7020000
0&
#7030000
b1101 8
1&
#7040000
0&
#7050000
b1110 8
1&
#7060000
0&
#7070000
b1111 8
1&
#7080000
0&
#7090000
b10000 8
1&
#7100000
0&
#7110000
b10001 8
1&
#7120000
0&
#7130000
b10010 8
1&
#7140000
0&
#7150000
b10011 8
1&
#7160000
0&
#7170000
b10100 8
1&
#7180000
0&
#7190000
b10101 8
1&
#7200000
0%
0&
#7210000
04
b10110 8
1&
#7220000
0&
#7230000
b10111 8
0)
05
1&
#7240000
0&
#7250000
b11000 8
1&
#7260000
0&
#7270000
b11001 8
1&
#7280000
0&
#7290000
b11010 8
1&
#7300000
0&
#7310000
b11011 8
1&
#7320000
0&
#7330000
b11100 8
1&
#7340000
0&
#7350000
b11101 8
1&
#7360000
0&
#7370000
b11110 8
1&
#7380000
0&
#7390000
b11111 8
1&
#7400000
0&
#7410000
b100000 8
1&
#7420000
0&
#7430000
b100001 8
1&
#7440000
0&
#7450000
b100010 8
1&
#7460000
0&
#7470000
b100011 8
1&
#7480000
0&
#7490000
b100100 8
1&
#7500000
0&
#7510000
b100101 8
1&
#7520000
0&
#7530000
b100110 8
1&
#7540000
0&
#7550000
b100111 8
1&
#7560000
0&
#7570000
b101000 8
1&
#7580000
0&
#7590000
b101001 8
1&
#7600000
0&
#7610000
b101010 8
1&
#7620000
0&
#7630000
b101011 8
1&
#7640000
0&
#7650000
b101100 8
1&
#7660000
0&
#7670000
b101101 8
1&
#7680000
0&
#7690000
b101110 8
1&
#7700000
0&
#7710000
b101111 8
1&
#7720000
0&
#7730000
b110000 8
1&
#7740000
0&
#7750000
b110001 8
1&
#7760000
0&
#7770000
b101 6
b0 8
1&
#7780000
0&
#7790000
b1 8
1&
#7800000
0&
#7810000
b10 8
1&
#7820000
0&
#7830000
b11 8
1&
#7840000
0&
#7850000
b100 8
1&
#7860000
0&
#7870000
b101 8
1&
#7880000
0&
#7890000
b110 8
1&
#7900000
0&
#7910000
b111 8
1&
#7920000
0&
#7930000
b1000 8
1&
#7940000
0&
#7950000
b1001 8
1&
#7960000
0&
#7970000
b1010 8
1&
#7980000
0&
#7990000
b1011 8
1&
#8000000
0&
#8010000
b1100 8
1&
#8020000
0&
#8030000
b1101 8
1&
#8040000
0&
#8050000
b1110 8
1&
#8060000
0&
#8070000
b1111 8
1&
#8080000
0&
#8090000
b10000 8
1&
#8100000
0&
#8110000
b10001 8
1&
#8120000
0&
#8130000
b10010 8
1&
#8140000
0&
#8150000
b10011 8
1&
#8160000
0&
#8170000
b10100 8
1&
#8180000
0&
#8190000
b10101 8
1&
#8200000
0&
#8210000
b10110 8
1&
#8220000
0&
#8230000
b10111 8
1&
#8240000
0&
#8250000
b11000 8
1&
#8260000
0&
#8270000
b11001 8
1&
#8280000
0&
#8290000
b11010 8
1&
#8300000
0&
#8310000
b11011 8
1&
#8320000
0&
#8330000
b11100 8
1&
#8340000
0&
#8350000
b11101 8
1&
#8360000
0&
#8370000
b11110 8
1&
#8380000
0&
#8390000
b11111 8
1&
#8400000
0&
#8410000
b100000 8
1&
#8420000
0&
#8430000
b100001 8
1&
#8440000
0&
#8450000
b100010 8
1&
#8460000
0&
#8470000
b100011 8
1&
#8480000
0&
#8490000
b100100 8
1&
#8500000
0&
#8510000
b100101 8
1&
#8520000
0&
#8530000
b100110 8
1&
#8540000
0&
#8550000
b100111 8
1&
#8560000
0&
#8570000
b101000 8
1&
#8580000
0&
#8590000
b101001 8
1&
#8600000
0&
#8610000
b101010 8
1&
#8620000
0&
#8630000
b101011 8
1&
#8640000
0&
#8650000
b101100 8
1&
#8660000
0&
#8670000
b101101 8
1&
#8680000
0&
#8690000
b101110 8
1&
#8700000
0&
#8710000
b101111 8
1&
#8720000
0&
#8730000
b110000 8
1&
#8740000
0&
#8750000
b110001 8
1&
#8760000
0&
#8770000
b110 6
b0 8
1&
#8780000
0&
#8790000
b1 8
1&
#8800000
0&
#8810000
b10 8
1&
#8820000
0&
#8830000
b11 8
1&
#8840000
0&
#8850000
b100 8
1&
#8860000
0&
#8870000
b101 8
1&
#8880000
0&
#8890000
b110 8
1&
#8900000
0&
#8910000
b111 8
1&
#8920000
0&
#8930000
b1000 8
1&
#8940000
0&
#8950000
b1001 8
1&
#8960000
0&
#8970000
b1010 8
1&
#8980000
0&
#8990000
b1011 8
1&
#9000000
0&
#9010000
b1100 8
1&
#9020000
0&
#9030000
b1101 8
1&
#9040000
0&
#9050000
b1110 8
1&
#9060000
0&
#9070000
b1111 8
1&
#9080000
0&
#9090000
b10000 8
1&
#9100000
0&
#9110000
b10001 8
1&
#9120000
0&
#9130000
b10010 8
1&
#9140000
0&
#9150000
b10011 8
1&
#9160000
0&
#9170000
b10100 8
1&
#9180000
0&
#9190000
b10101 8
1&
#9200000
1%
0&
#9210000
14
b10110 8
1&
#9220000
0&
#9230000
b10111 8
1)
15
1&
#9240000
0&
#9250000
b11000 8
1&
#9260000
0&
#9270000
b11001 8
1&
#9280000
0&
#9290000
b11010 8
1&
#9300000
0&
#9310000
b11011 8
1&
#9320000
0&
#9330000
b11100 8
1&
#9340000
0&
#9350000
b11101 8
1&
#9360000
0&
#9370000
b11110 8
1&
#9380000
0&
#9390000
b11111 8
1&
#9400000
0&
#9410000
b100000 8
1&
#9420000
0&
#9430000
b100001 8
1&
#9440000
0&
#9450000
b100010 8
1&
#9460000
0&
#9470000
b100011 8
1&
#9480000
0&
#9490000
b100100 8
1&
#9500000
0&
#9510000
b100101 8
1&
#9520000
0&
#9530000
b100110 8
1&
#9540000
0&
#9550000
b100111 8
1&
#9560000
0&
